anton_util.py
anton_util-0.0.2.dist-info/METADATA
anton_util-0.0.2.dist-info/WHEEL
anton_util-0.0.2.dist-info/top_level.txt
anton_util-0.0.2.dist-info/RECORD
