Metadata-Version: 2.1
Name: anton_util
Version: 0.0.2
Summary: Some small Python utilities for everyday convenience
Author-email: Anton Björk <to.anton.bjork@gmail.com>
Project-URL: Homepage, https://github.com/anbjork/anton_util
Project-URL: Issues, https://github.com/anbjork/anton_util/issues
Classifier: Programming Language :: Python :: 3
Classifier: Operating System :: OS Independent
